Metadata-Version: 2.1
Name: imx-openzeppelin-cairo-contracts
Version: 0.5.0
Summary: Library for secure smart contract development written in Cairo
Home-page: https://github.com/immutable/cairo-contracts
Author: Immutable X + OpenZeppelin Community
Author-email: starknet-security@immutable.com
License: MIT
Platform: any
Classifier: Operating System :: OS Independent
License-File: LICENSE
Requires-Dist: importlib-metadata (>=4.0)
Provides-Extra: testing
Requires-Dist: setuptools ; extra == 'testing'
Requires-Dist: tox ; extra == 'testing'
Requires-Dist: pytest ; extra == 'testing'
